[
  {
    "templename": "Gayathri Mandira",
    "address": "11th Cross Road, 1st Stage, Kengeri Satelite Town, Bangalore - 560060"
  },
  {
    "templename": "Shri Abhaya Hasta Balamuri Ganapathi Temple",
    "address": "Stage Ii, Kengeri Satellite Town, Bengaluru, Duvasapalya, Bangalore - 560060"
  },
  {
    "templename": "Matsya Narayana Devasthana",
    "address": "Shrinivasapura, Kengeri, Bangalore - 560060 (Behind Jss Engineering College)"
  },
  {
    "templename": "Balamuri Mahaganapathi Rajarajeshwari Temple",
    "address": "8th Cross Road, Volagalahalli, Stage 2, Kengeri Satelite Town, Bangalore - 560060"
  },
  {
    "templename": "Shri Vishwavidya Ganesha Temple",
    "address": "Stage Ii, Kengeri Satellite Town, Kengeri, Bangalore - 560060"
  },
  {
    "templename": "Gutte Anjaneya Swamy Temple",
    "address": "No 57/3, Uttarahalli Kengeri Main Road, Kengeri, Bangalore - 560060"
  },
  {
    "templename": "Kalikamba Temple",
    "address": "454, Stage I, Kengeri Satellite Town, Bengaluru, 5th Main Road, Kengeri, Bangalore - 560060"
  },
  {
    "templename": "Sri Sri Bandeshwara Swamy Shivayogigala Bhavana",
    "address": "6035/193/2, Bande Matt, Suncity, Kengeri Satellite Town, Bengaluru, Bsm Extension, Bangalore - 560060"
  },
  {
    "templename": "Sri Raghavendra Swamy Mutt",
    "address": "3rd Main Road, Kengeri, Bangalore - 560060 (Near Corporation Bank)"
  },
  {
    "templename": "Dwadasha Jyotirlinga",
    "address": "Omkar Hills, Shrinivasapura, Srinivaspura, Bangalore - 560060"
  }
]